nn4n/__init__.py
nn4n/utils.py
nn4n/constraint/__init__.py
nn4n/constraint/weight_constraints.py
nn4n/criterion/__init__.py
nn4n/criterion/mlp_loss.py
nn4n/criterion/rnn_loss.py
nn4n/layer/__init__.py
nn4n/layer/hidden_layer.py
nn4n/layer/linear_layer.py
nn4n/layer/recurrent_layer.py
nn4n/mask/__init__.py
nn4n/mask/base_mask.py
nn4n/mask/base_struct.py
nn4n/mask/multi_area.py
nn4n/mask/multi_area_ei.py
nn4n/mask/random_input.py
nn4n/model/__init__.py
nn4n/model/base_nn.py
nn4n/model/ctrnn.py
nn4n/model/mlp.py
nn4n/structure/__init__.py
nn4n/structure/base_struct.py
nn4n/structure/multi_area.py
nn4n/structure/multi_area_ei.py
nn4n/structure/random_input.py
nn4n-1.1.1.dist-info/LICENSE
nn4n-1.1.1.dist-info/METADATA
nn4n-1.1.1.dist-info/WHEEL
nn4n-1.1.1.dist-info/top_level.txt
nn4n-1.1.1.dist-info/RECORD
