Metadata-Version: 2.1
Name: nn4n
Version: 1.1.1
Summary: Neural Networks for Neurosimulation
Author: Zhaoze Wang
License: MIT
Requires-Python: >=3.10
License-File: LICENSE
Requires-Dist: numpy
Requires-Dist: matplotlib
Requires-Dist: torch
Requires-Dist: IPython
Requires-Dist: scipy
